mylib_011/__init__.py
mylib_011-0.1.dist-info/LICENSE.txt
mylib_011-0.1.dist-info/METADATA
mylib_011-0.1.dist-info/WHEEL
mylib_011-0.1.dist-info/top_level.txt
mylib_011-0.1.dist-info/RECORD
